secure_web3/__init__.py
secure_web3/sw3.py
secure_web3/sw3_wallet.py
secure_web3/data/networks.json
secure_web3/keys/default_wallet.json
secure_web3/lib/abi_lib.py
secure_web3/lib/inputs.py
secure_web3/lib/load_networks.py
secure_web3/lib/style.py
secure_web3/lib/w3_validation.py
secure_web3/lib/wallet_manager.py
secure_web3-1.3.2.data/data/default_wallet.json
secure_web3-1.3.2.data/data/networks.json
secure_web3-1.3.2.dist-info/LICENSE.txt
secure_web3-1.3.2.dist-info/METADATA
secure_web3-1.3.2.dist-info/WHEEL
secure_web3-1.3.2.dist-info/top_level.txt
secure_web3-1.3.2.dist-info/RECORD
