Metadata-Version: 2.1
Name: secure-web3
Version: 1.3.2
Summary: Secure wallet and development enviroment
Home-page: https://github.com/darkerego/secure_web3
Author: darkerego
Author-email: Darkergo <chevisyoung@gmail.com>
License: MIT
Project-URL: Homepage, https://github.com/darkerego/secure_web3
Project-URL: Bug Tracker, https://github.com/darkerego/secure_web3/issues
Classifier: Programming Language :: Python :: 3
Classifier: License :: OSI Approved :: MIT License
Classifier: Operating System :: OS Independent
Requires-Python: >=3.7
License-File: LICENSE.txt
Requires-Dist: web3
Requires-Dist: pycryptodome
Requires-Dist: python-dotenv
Requires-Dist: eth-utils
Requires-Dist: colored
